molclustpy/DataViz_NFsim.py
molclustpy/HelperFunctions.py
molclustpy/MultiRun_BNG.py
molclustpy/NFsim_data_analyzer.py
molclustpy/__init__.py
molclustpy-0.1.0.dist-info/LICENCE.txt
molclustpy-0.1.0.dist-info/METADATA
molclustpy-0.1.0.dist-info/WHEEL
molclustpy-0.1.0.dist-info/top_level.txt
molclustpy-0.1.0.dist-info/RECORD
