Metadata-Version: 2.1
Name: molclustpy
Version: 0.1.0
Summary: A Python package to analyze multivalent biomolecular clustering.
Home-page: https://molclustpy.github.io/
Author: Aniruddha Chattaraj, Michael Blinov, Indivar Nalagandla
Author-email: chattarajaniruddha@gmail.com
License: MIT License
Keywords: BioNetGen,NumPy,Matplotlib,pandas,,
Platform: UNKNOWN
Classifier: Development Status :: 1 - Planning
Classifier: Intended Audience :: Developers
Classifier: Programming Language :: Python :: 3
Classifier: Operating System :: Unix
Classifier: Operating System :: MacOS :: MacOS X
Classifier: Operating System :: Microsoft :: Windows
License-File: LICENCE.txt
